README.md
setup.cfg
setup.py
gpretty/__init__.py
gpretty.egg-info/PKG-INFO
gpretty.egg-info/SOURCES.txt
gpretty.egg-info/dependency_links.txt
gpretty.egg-info/top_level.txt
gpretty/command_utils/__init__.py
gpretty/command_utils/prettify.py