Metadata-Version: 1.1
Name: gpretty
Version: 0.2.1
Summary: A collection of tools for prettifying commands
Home-page: https://github.com/giftig/gpretty
Author: Rob Moore
Author-email: giftiger.wunsch@xantoria.com
License: UNKNOWN
Download-URL: https://github.com/giftig/gpretty/archive/0.1.tar.gz
Keywords: pretty,prettify,commands,scripts
Platform: UNKNOWN
